CHANGES.txt
MANIFEST.in
README.txt
env_pysca.sh
setup.py
bin/pysca
examples/example.py
licenses/LICENSE.txt
licenses/LICENSE_argparse.txt
pysca/__init__.py
pysca/_argparse.py
pysca/_fasper.py
pysca/app.py
pysca/core.py
pysca/fit.py
pysca/io.py
pysca/utils.py
pysca.egg-info/PKG-INFO
pysca.egg-info/SOURCES.txt
pysca.egg-info/dependency_links.txt
pysca.egg-info/requires.txt
pysca.egg-info/top_level.txt