Metadata-Version: 1.1
Name: pysca
Version: 0.1.2
Summary: A tool for automated frequency extraction from photometric time series of heat-driven pulsators.
Home-page: http://pypi.python.org/pypi/pysca
Author: Wiebke Herzberg, Kolja Glogowski
Author-email: "Kolja Glogowski" <kolja@kis.uni-freiburg.de>
License: MIT
Platform: UNKNOWN
Classifier: Development Status :: 3 - Alpha
Classifier: Environment :: Console
Classifier: Intended Audience :: Science/Research
Classifier: License :: OSI Approved :: MIT License
Classifier: Operating System :: OS Independent
Classifier: Programming Language :: Python
Classifier: Programming Language :: Python :: 2.6
Classifier: Programming Language :: Python :: 2.7
Classifier: Topic :: Scientific/Engineering :: Astronomy
